MANIFEST.in
README.rst
buildout.cfg
setup.cfg
setup.py
tox.ini
docs/Makefile
docs/api.rst
docs/api_fixt.py
docs/conf.py
docs/index.rst
docs/index_fixt.py
tests/__init__.py
tests/image.jpg
tests/settings.py
tests/test_wsgithumb.py
wsgithumb/__init__.py
wsgithumb/django_view.py
wsgithumb/utils.py
wsgithumb.egg-info/PKG-INFO
wsgithumb.egg-info/SOURCES.txt
wsgithumb.egg-info/dependency_links.txt
wsgithumb.egg-info/entry_points.txt
wsgithumb.egg-info/not-zip-safe
wsgithumb.egg-info/requires.txt
wsgithumb.egg-info/top_level.txt