Metadata-Version: 1.1
Name: wsgithumb
Version: 0.2
Summary: helpers to get a WebOb response to serve static files and thumbnails in an efficient way
Home-page: http://github.com/gawel/wsgithumb
Author: Gael Pasgrimaud
Author-email: gael@gawel.org
License: MIT
Keywords: pyramid wsgi thumbnail PIL X-Sendfile X-Accel-Redirect
Platform: UNKNOWN
Classifier: Framework :: Pylons
Classifier: License :: OSI Approved :: MIT License
Classifier: Topic :: Internet :: WWW/HTTP :: WSGI
